apeer_ometiff_library/__init__.py
apeer_ometiff_library/io.py
apeer_ometiff_library/omexmlClass.py
apeer_ometiff_library/processing.py
tests/__init__.py
tests/test_io.py
apeer_ometiff_library-1.11.0.dist-info/LICENSE
apeer_ometiff_library-1.11.0.dist-info/METADATA
apeer_ometiff_library-1.11.0.dist-info/WHEEL
apeer_ometiff_library-1.11.0.dist-info/top_level.txt
apeer_ometiff_library-1.11.0.dist-info/RECORD
