Metadata-Version: 2.1
Name: apeer-ometiff-library
Version: 1.11.0
Summary: Library to read and write ometiff images
Home-page: https://github.com/apeer-micro/apeer-ometiff-library
Author: apeer-micro
License: MIT
Platform: UNKNOWN
Classifier: Programming Language :: Python :: 3
Classifier: License :: OSI Approved :: MIT License
Classifier: Operating System :: OS Independent
License-File: LICENSE
Requires-Dist: numpy >=1.18.5
Requires-Dist: tifffile >=2020.9.30
Requires-Dist: imagecodecs >=2023.9.18
